zvartools/__init__.py
zvartools/candidate.py
zvartools/data.py
zvartools/enums.py
zvartools/external.py
zvartools/lightcurves.py
zvartools/parsers.py
zvartools/periodicity.py
zvartools/plot.py
zvartools/spatial.py
zvartools/stats.py
zvartools-0.1.2.dist-info/METADATA
zvartools-0.1.2.dist-info/WHEEL
zvartools-0.1.2.dist-info/top_level.txt
zvartools-0.1.2.dist-info/RECORD
