Metadata-Version: 2.2
Name: zvartools
Version: 0.1.2
Summary: A collection of tools for working with ZVAR data.
Requires-Python: <3.12,>=3.9
Requires-Dist: numpy<2
Requires-Dist: pandas
Requires-Dist: astropy
Requires-Dist: penquins
Requires-Dist: paramiko
Requires-Dist: scp
Requires-Dist: pyarrow
Requires-Dist: fastparquet
Requires-Dist: numba
Requires-Dist: h5py
Requires-Dist: tqdm
Requires-Dist: matplotlib
Requires-Dist: fpwperiodic
Provides-Extra: dev
Requires-Dist: pre-commit; extra == "dev"
Requires-Dist: pytest; extra == "dev"
